<?xml version='1.0' encoding='UTF-8'?><ts><start>s0</start><states><state id="s3"><transition target="sX" action="epsilon" proba="1.0" /></state><state id="s4"><transition target="sX" action="epsilon" proba="1.0" /></state><state id="sX"><transition target="s0" action="epsilon" proba="1.0" /></state><state id="s0"><transition target="s4" action="java.util.ArrayList.iterator()" proba="0.0196078431372549" /><transition target="s1" action="java.util.ArrayList.&lt;init>()" proba="0.9803921568627451" /></state><state id="s1"><transition target="s3" action="java.util.ArrayList.size()" proba="0.018867924528301886" /><transition target="sX" action="epsilon" proba="0.05660377358490566" /><transition target="s2" action="java.util.ArrayList.add(java.lang.Object)" proba="0.9245283018867925" /></state><state id="s2"><transition target="sX" action="epsilon" proba="0.6666666666666666" /><transition target="s1" action="java.util.ArrayList.&lt;init>()" proba="0.043478260869565216" /><transition target="s2" action="java.util.ArrayList.add(java.lang.Object)" proba="0.2898550724637681" /></state></states></ts>