<?xml version='1.0' encoding='UTF-8'?><ts><start>s0</start><states><state id="s3"><transition target="sX" action="epsilon" proba="1.0" /></state><state id="sX"><transition target="s0" action="epsilon" proba="1.0" /></state><state id="s0"><transition target="s3" action="org.wso2.carbon.um.ws.api.WSRealmUtil.convertToClaims(org.wso2.carbon.um.ws.api.stub.ClaimDTO[])" proba="0.2" /><transition target="s1" action="org.wso2.carbon.um.ws.api.WSRealmUtil.convertMapToClaimValue(java.util.Map)" proba="0.6" /><transition target="s2" action="org.wso2.carbon.um.ws.api.WSRealmUtil.convertClaimValuesToMap(org.wso2.carbon.um.ws.api.stub.ClaimValue[])" proba="0.2" /></state><state id="s1"><transition target="sX" action="epsilon" proba="1.0" /></state><state id="s2"><transition target="sX" action="epsilon" proba="1.0" /></state></states></ts>